chattychattybangbang/__init__.py
chattychattybangbang/castigateuntilvalid.py
chattychattybangbang/castigateuntilvaluesare.py
chattychattybangbang/castigators.py
chattychattybangbang/jsonutil.py
chattychattybangbang/openaicredentials.py
chattychattybangbang/openutil.py
chattychattybangbang/validators.py
chattychattybangbang/whereami.py
chattychattybangbang-0.0.27.dist-info/LICENSE
chattychattybangbang-0.0.27.dist-info/METADATA
chattychattybangbang-0.0.27.dist-info/WHEEL
chattychattybangbang-0.0.27.dist-info/entry_points.txt
chattychattybangbang-0.0.27.dist-info/top_level.txt
chattychattybangbang-0.0.27.dist-info/RECORD
